{
	"$schema": "http://schema.management.azure.com/schemas/2015-01-01/deploymentTemplate.json#",
	"contentVersion": "1.0.0.0",
	"parameters": {
		"factoryName": {
			"type": "string",
			"metadata": "Data Factory name",
			"defaultValue": "myfactory127"
		},
		"AzureBlobStorageLS_connectionString": {
			"type": "secureString",
			"metadata": "Secure string for 'connectionString' of 'AzureBlobStorageLS'"
		},
		"AzureDataLakeStorageLS_accountKey": {
			"type": "secureString",
			"metadata": "Secure string for 'accountKey' of 'AzureDataLakeStorageLS'"
		},
		"AzureDataLakeStorageLS_properties_typeProperties_url": {
			"type": "string",
			"defaultValue": "https://detalakestorage.dfs.core.windows.net/"
		},
		"AzureDatabricksLS_properties_typeProperties_existingClusterId": {
			"type": "string",
			"defaultValue": "0129-161902-l23uwmjk"
		},
		"AzureKeyVaultLS_properties_typeProperties_baseUrl": {
			"type": "string",
			"defaultValue": "https://kvsaccount12.vault.azure.net/"
		}
	},
	"variables": {
		"factoryId": "[concat('Microsoft.DataFactory/factories/', parameters('factoryName'))]"
	},
	"resources": [
		{
			"name": "[concat(parameters('factoryName'), '/DATASETBOLB')]",
			"type": "Microsoft.DataFactory/factories/datasets",
			"apiVersion": "2018-06-01",
			"properties": {
				"linkedServiceName": {
					"referenceName": "AzureBlobStorageLS",
					"type": "LinkedServiceReference"
				},
				"annotations": [],
				"type": "DelimitedText",
				"typeProperties": {
					"location": {
						"type": "AzureBlobStorageLocation",
						"container": "input"
					},
					"columnDelimiter": ",",
					"escapeChar": "\\",
					"firstRowAsHeader": true,
					"quoteChar": "\""
				},
				"schema": []
			},
			"dependsOn": [
				"[concat(variables('factoryId'), '/linkedServices/AzureBlobStorageLS')]"
			]
		},
		{
			"name": "[concat(parameters('factoryName'), '/DATASETSGEN2')]",
			"type": "Microsoft.DataFactory/factories/datasets",
			"apiVersion": "2018-06-01",
			"properties": {
				"linkedServiceName": {
					"referenceName": "AzureDataLakeStorageLS",
					"type": "LinkedServiceReference"
				},
				"annotations": [],
				"type": "DelimitedText",
				"typeProperties": {
					"location": {
						"type": "AzureBlobFSLocation",
						"folderPath": "sales",
						"fileSystem": "output"
					},
					"columnDelimiter": ",",
					"escapeChar": "\\",
					"firstRowAsHeader": true,
					"quoteChar": "\""
				},
				"schema": []
			},
			"dependsOn": [
				"[concat(variables('factoryId'), '/linkedServices/AzureDataLakeStorageLS')]"
			]
		},
		{
			"name": "[concat(parameters('factoryName'), '/AzureBlobStorageLS')]",
			"type": "Microsoft.DataFactory/factories/linkedServices",
			"apiVersion": "2018-06-01",
			"properties": {
				"annotations": [],
				"type": "AzureBlobStorage",
				"typeProperties": {
					"connectionString": "[parameters('AzureBlobStorageLS_connectionString')]"
				}
			},
			"dependsOn": []
		},
		{
			"name": "[concat(parameters('factoryName'), '/AzureDataLakeStorageLS')]",
			"type": "Microsoft.DataFactory/factories/linkedServices",
			"apiVersion": "2018-06-01",
			"properties": {
				"annotations": [],
				"type": "AzureBlobFS",
				"typeProperties": {
					"url": "[parameters('AzureDataLakeStorageLS_properties_typeProperties_url')]",
					"accountKey": {
						"type": "SecureString",
						"value": "[parameters('AzureDataLakeStorageLS_accountKey')]"
					}
				}
			},
			"dependsOn": []
		},
		{
			"name": "[concat(parameters('factoryName'), '/AzureDatabricksLS')]",
			"type": "Microsoft.DataFactory/factories/linkedServices",
			"apiVersion": "2018-06-01",
			"properties": {
				"annotations": [],
				"type": "AzureDatabricks",
				"typeProperties": {
					"domain": "https://adb-1399731311845973.13.azuredatabricks.net",
					"accessToken": {
						"type": "AzureKeyVaultSecret",
						"store": {
							"referenceName": "AzureKeyVaultLS",
							"type": "LinkedServiceReference"
						},
						"secretName": "datatoken"
					},
					"existingClusterId": "[parameters('AzureDatabricksLS_properties_typeProperties_existingClusterId')]"
				}
			},
			"dependsOn": [
				"[concat(variables('factoryId'), '/linkedServices/AzureKeyVaultLS')]"
			]
		},
		{
			"name": "[concat(parameters('factoryName'), '/AzureKeyVaultLS')]",
			"type": "Microsoft.DataFactory/factories/linkedServices",
			"apiVersion": "2018-06-01",
			"properties": {
				"annotations": [],
				"type": "AzureKeyVault",
				"typeProperties": {
					"baseUrl": "[parameters('AzureKeyVaultLS_properties_typeProperties_baseUrl')]"
				}
			},
			"dependsOn": []
		}
	]
}